nems/__init__.py
nems/registry.py
nems/backends/__init__.py
nems/backends/base.py
nems/backends/scipy/__init__.py
nems/backends/scipy/backend.py
nems/backends/scipy/cost.py
nems/backends/tf/__init__.py
nems/backends/tf/backend.py
nems/backends/tf/cost.py
nems/backends/tf/layer_tools.py
nems/distributions/__init__.py
nems/distributions/base.py
nems/distributions/beta.py
nems/distributions/exponential.py
nems/distributions/gamma.py
nems/distributions/half_normal.py
nems/distributions/normal.py
nems/distributions/uniform.py
nems/layers/__init__.py
nems/layers/algebra.py
nems/layers/filter.py
nems/layers/nonlinearity.py
nems/layers/numpy.py
nems/layers/state.py
nems/layers/stp.py
nems/layers/tools.py
nems/layers/weight_channels.py
nems/layers/base/__init__.py
nems/layers/base/errors.py
nems/layers/base/layer.py
nems/layers/base/map.py
nems/layers/base/parameter.py
nems/layers/base/phi.py
nems/metrics/__init__.py
nems/metrics/correlation.py
nems/models/LN.py
nems/models/__init__.py
nems/models/base.py
nems/models/dataset.py
nems/preprocessing/__init__.py
nems/preprocessing/filters.py
nems/preprocessing/mask.py
nems/preprocessing/merge.py
nems/preprocessing/normalization.py
nems/preprocessing/raster.py
nems/preprocessing/split.py
nems/preprocessing/spectrogram/__init__.py
nems/preprocessing/spectrogram/fft.py
nems/preprocessing/spectrogram/filters.py
nems/preprocessing/spectrogram/gammatone.py
nems/tools/__init__.py
nems/tools/arrays.py
nems/tools/debug.py
nems/tools/io.py
nems/tools/json.py
nems/tools/lookup.py
nems/tools/demo_data/__init__.py
nems/tools/demo_data/file_management.py
nems/visualization/__init__.py
nems/visualization/fitter.py
nems/visualization/layers.py
nems/visualization/model.py
nems/visualization/tools.py
PyNEMS-0.0.3.dist-info/LICENSE
PyNEMS-0.0.3.dist-info/METADATA
PyNEMS-0.0.3.dist-info/WHEEL
PyNEMS-0.0.3.dist-info/top_level.txt
PyNEMS-0.0.3.dist-info/RECORD
