Metadata-Version: 2.1
Name: PyNEMS
Version: 0.0.3
Summary: Fit and evaluate models of sensory encoding and decoding.
Author-email: Jacob Pennington <jacob.p.neuro@gmail.com>, Stephen David <lbhb.ohsu@gmail.com>
License: GNU GENERAL PUBLIC LICENSE
Project-URL: Homepage, https://github.com/LBHB/NEMS
Keywords: neuroscience,auditory,sensory,encoding,strf
Classifier: License :: OSI Approved :: GNU General Public License v3 (GPLv3)
Classifier: Programming Language :: Python :: 3 :: Only
Requires-Python: >=3.9
License-File: LICENSE
Requires-Dist: numpy (>=1.21.5)
Requires-Dist: scipy (>=1.9.0)
Requires-Dist: matplotlib (>=3.5.2)
Requires-Dist: numexpr (>=2.8.3)
Requires-Dist: numba (>=0.55.1)
Provides-Extra: dev
Requires-Dist: build ; extra == 'dev'
Requires-Dist: twine ; extra == 'dev'
Requires-Dist: pytest ; extra == 'dev'
Provides-Extra: tf
Requires-Dist: tensorflow (>=2.9) ; extra == 'tf'
